yurlungur/Qt.py
yurlungur/__init__.py
yurlungur/__main__.py
yurlungur/adapters/__init__.py
yurlungur/adapters/blender.py
yurlungur/adapters/c4d.py
yurlungur/adapters/davinci.py
yurlungur/adapters/houdini.py
yurlungur/adapters/max.py
yurlungur/adapters/maya.py
yurlungur/adapters/nuke.py
yurlungur/adapters/photoshop.py
yurlungur/adapters/substance.py
yurlungur/adapters/ue4.py
yurlungur/adapters/unity.py
yurlungur/core/__init__.py
yurlungur/core/app.py
yurlungur/core/command.py
yurlungur/core/deco.py
yurlungur/core/env.py
yurlungur/core/logger.py
yurlungur/core/nodetype.py
yurlungur/core/proxy.py
yurlungur/core/wrapper.py
yurlungur/tool/__init__.py
yurlungur/tool/editor.py
yurlungur/tool/graph.py
yurlungur/tool/meta.py
yurlungur/tool/standalone.py
yurlungur/tool/ui.py
yurlungur/user/__init__.py
yurlungur/user/dark.css
yurlungur/user/init_unreal.py
yurlungur/user/pythonrc.py
yurlungur/user/usersetup.py
yurlungur-0.9.7.dist-info/LICENSE.md
yurlungur-0.9.7.dist-info/METADATA
yurlungur-0.9.7.dist-info/WHEEL
yurlungur-0.9.7.dist-info/top_level.txt
yurlungur-0.9.7.dist-info/RECORD
