Metadata-Version: 2.1
Name: yurlungur
Version: 0.9.7
Summary: universal scripting environment with Python which Maya, Houdini and UnrealEngine.
Home-page: https://sho7noka.github.io/Yurlungur/
Author: sho7noka
Author-email: shosumioka@gmail.com
License: MIT
Keywords: maya,3d,graphics,Game,VFX,CG,houdini,unreal
Platform: any
